fy_library/__init__.py
fy_library/constants.py
fy_library/domain/__init__.py
fy_library/domain/annotation_object.py
fy_library/domain/entity_key.py
fy_library/domain/fy_py_template_models.py
fy_library/domain/mixin_models.py
fy_library/domain/parsed_fy_py_file.py
fy_library/domain/parsed_fy_py_file_kind.py
fy_library/domain/python_entity_name.py
fy_library/fc.py
fy_library/flows/__init__.py
fy_library/flows/create_template_model_using_parsed_fy_py_file/__init__.py
fy_library/flows/create_template_model_using_parsed_fy_py_file/abstract_method_template_model_fy.py
fy_library/flows/create_template_model_using_parsed_fy_py_file/abstract_property_template_model_fy.py
fy_library/flows/create_template_model_using_parsed_fy_py_file/base_flow_template_model_fy.py
fy_library/flows/create_template_model_using_parsed_fy_py_file/flow_template_model_fy.py
fy_library/flows/create_template_model_using_parsed_fy_py_file/main_fy.py
fy_library/flows/create_template_model_using_parsed_fy_py_file/method_template_model_fy.py
fy_library/flows/create_template_model_using_parsed_fy_py_file/property_setter_template_model_fy.py
fy_library/flows/create_template_model_using_parsed_fy_py_file/property_template_model_fy.py
fy_library/flows/flow_compose_main_fy.py
fy_library/flows/fy_py_main_fy.py
fy_library/flows/generate_and_save_flow_compose_file__using_parsed_fy_py_file_fy.py
fy_library/flows/generate_and_save_flow_compose_files__using_parsed_fy_py_files_fy.py
fy_library/flows/generate_and_save_fy_py_file__using_parsed_fy_py_file_fy.py
fy_library/flows/generate_and_save_fy_py_file__using_required_property_setters_fy.py
fy_library/flows/generate_and_save_fy_py_files__using_parsed_fy_py_files_fy.py
fy_library/flows/generate_and_save_fy_py_files__using_required_property_setters_fy.py
fy_library/flows/imports/__init__.py
fy_library/flows/imports/abstract_method_imports_fy.py
fy_library/flows/imports/abstract_property_imports_fy.py
fy_library/flows/imports/base_flow_imports_fy.py
fy_library-0.5.21.dist-info/LICENSE
fy_library-0.5.21.dist-info/METADATA
fy_library-0.5.21.dist-info/WHEEL
fy_library-0.5.21.dist-info/RECORD
