Metadata-Version: 2.3
Name: fy_library
Version: 0.5.21
Summary: Implementation of fy tool functionality - parsing and generating.
Author: Vinko Buble
Author-email: vinkobuble@gmail.com
Requires-Python: >=3.10,<3.14
Classifier: Programming Language :: Python :: 3
Classifier: Programming Language :: Python :: 3.10
Classifier: Programming Language :: Python :: 3.11
Classifier: Programming Language :: Python :: 3.12
Classifier: Programming Language :: Python :: 3.13
Requires-Dist: fy-core (==0.1.2)
Requires-Dist: jinja2 (>=3.1.4,<4.0.0)
Requires-Dist: pydantic (>=2.8.2,<3.0.0)
